Metadata-Version: 2.1
Name: virtualenv-update-path
Version: 0.0.1
Summary: Add folders to path for a virtual environment
Home-page: https://github.com/SindreOsnes/virtualenv-update-path
Author: Sindre Osnes
Author-email: sindreosnes.git@gmail.com
Requires-Python: >=3.7
